LICENSE
MANIFEST.in
README.rst
setup.cfg
setup.py
versioneer.py
artellapipe/__init__.py
artellapipe/tools/__init__.py
artellapipe/tools/changelog/__init__.py
artellapipe/tools/changelog/__logging__.ini
artellapipe/tools/changelog/__version__.py
artellapipe/tools/changelog/_version.py
artellapipe/tools/changelog/core/__init__.py
artellapipe/tools/changelog/core/changelog.py
artellapipe/tools/changelog/resources/images/changelog_logo.png
artellapipe/tools/changelog/widgets/__init__.py
artellapipe/tools/changelog/widgets/changelog.py
artellapipe_tools_changelog.egg-info/PKG-INFO
artellapipe_tools_changelog.egg-info/SOURCES.txt
artellapipe_tools_changelog.egg-info/dependency_links.txt
artellapipe_tools_changelog.egg-info/not-zip-safe
artellapipe_tools_changelog.egg-info/requires.txt
artellapipe_tools_changelog.egg-info/top_level.txt
tests/__init__.py
tests/test_general.py