Metadata-Version: 2.1
Name: artellapipe-tools-changelog
Version: 0.0.6
Summary: Tool that shows generic changelog for Artella project
Home-page: https://github.com/ArtellaPipe/artellapipe-tools-changelog
Author: Tomas Poveda
Author-email: tpovedatd@gmail.com
License: MIT
Platform: UNKNOWN
Provides-Extra: dev
Provides-Extra: test
